xeni/__init__.py
xeni/cli.py
xeni/http_proxy/server.py
xeni/http_proxy/endpoints/__init__.py
xeni/http_proxy/endpoints/healthcheck.py
xeni/http_proxy/endpoints/insert.py
xeni/http_proxy/endpoints/search.py
xeni/mcp_proxy/server.py
xeni/mcp_proxy/adapters/__init__.py
xeni/mcp_proxy/adapters/base.py
xeni/mcp_proxy/adapters/claude.py
xeni/mcp_proxy/adapters/cline.py
xeni/mcp_proxy/adapters/cursor.py
xeni/utils/__init__.py
xeni/utils/config.py
xeni/utils/file_manager.py
xeni/utils/models.py
xeni-0.1.1.dist-info/METADATA
xeni-0.1.1.dist-info/WHEEL
xeni-0.1.1.dist-info/entry_points.txt
xeni-0.1.1.dist-info/RECORD
