Metadata-Version: 2.4
Name: xeni
Version: 0.1.1
Summary: xeni - A CLI program to manage all your MCPs
Author-email: Suchetan Chakraborty <suchetan005@gmail.com>
License-Expression: MIT
Keywords: AI,cli-mcp-manager,fastapi,mcp,xeni
Classifier: Development Status :: 4 - Beta
Classifier: Environment :: Console
Classifier: Intended Audience :: End Users/Desktop
Classifier: License :: OSI Approved :: MIT License
Classifier: Operating System :: OS Independent
Classifier: Programming Language :: Python :: 3
Classifier: Programming Language :: Python :: 3.9
Classifier: Programming Language :: Python :: 3.10
Classifier: Programming Language :: Python :: 3.11
Classifier: Topic :: Multimedia :: Sound/Audio :: Players
Requires-Python: >=3.11
Requires-Dist: click>=8.2.1
Requires-Dist: fastapi>=0.115.13
Requires-Dist: httpx>=0.28.1
Requires-Dist: mcp>=1.9.4
Requires-Dist: pydantic>=2.11.7
Requires-Dist: uvicorn>=0.34.3
